Metadata-Version: 2.1
Name: pysellure
Version: 0.0.3
Summary: Python/Selenium/Allure methods
Home-page: UNKNOWN
Author: Dmitry Vinogradov
Author-email: dvinogradov@htsts.ru
License: UNKNOWN
Keywords: python,selenium,allure,autotesting
Platform: UNKNOWN
Classifier: Programming Language :: Python :: 3
Classifier: License :: OSI Approved :: MIT License
Classifier: Operating System :: OS Independent
Requires-Python: >=3.6
License-File: LICENSE
